beanhub_inbox/__init__.py
beanhub_inbox/data_types.py
beanhub_inbox/llm.py
beanhub_inbox/processor.py
beanhub_inbox/templates.py
beanhub_inbox/utils.py
beanhub_inbox-0.2.3.dist-info/METADATA
beanhub_inbox-0.2.3.dist-info/WHEEL
beanhub_inbox-0.2.3.dist-info/licenses/LICENSE
beanhub_inbox-0.2.3.dist-info/RECORD
