Metadata-Version: 2.4
Name: beanhub-inbox
Version: 0.2.3
Summary: Email processing engine for archiving and extracting financial data
License-File: LICENSE
Requires-Python: >=3.10
Requires-Dist: email-validator>=2.2.0
Requires-Dist: jinja2>=3.1.6
Requires-Dist: lxml>=5.3.2
Requires-Dist: ollama>=0.4.7
Requires-Dist: pydantic>=2.11.2
Requires-Dist: pyyaml>=6.0.2
